tests/__init__.py
tests/test_settings.py
tests/tests.py
tests/urls.py
wagtail_stacks_featuredlink/__init__.py
wagtail_stacks_featuredlink/apps.py
wagtail_stacks_featuredlink/blocks.py
wagtail_stacks_featuredlink/registered_blocks.py
wagtail_stacks_featuredlink/templates/wagtail_stacks_featuredlink/anchor-tag.html
wagtail_stacks_featuredlink/templates/wagtail_stacks_featuredlink/button.html
wagtail_stacks_featuredlink/templates/wagtail_stacks_featuredlink/list/1up.html
wagtail_stacks_featuredlink/templates/wagtail_stacks_featuredlink/list/2up.html
wagtail_stacks_featuredlink/templates/wagtail_stacks_featuredlink/list/3up.html
wagtail_stacks_featuredlink/templates/wagtail_stacks_featuredlink/list/list-item.html
wagtail_stacks_featuredlink-0.1.dist-info/DESCRIPTION.rst
wagtail_stacks_featuredlink-0.1.dist-info/LICENSE.txt
wagtail_stacks_featuredlink-0.1.dist-info/METADATA
wagtail_stacks_featuredlink-0.1.dist-info/RECORD
wagtail_stacks_featuredlink-0.1.dist-info/WHEEL
wagtail_stacks_featuredlink-0.1.dist-info/metadata.json
wagtail_stacks_featuredlink-0.1.dist-info/top_level.txt
